scales/__init__.py
scales/asynchronous.py
scales/binary.py
scales/compat.py
scales/constants.py
scales/core.py
scales/dispatch.py
scales/message.py
scales/observable.py
scales/resurrector.py
scales/scales_socket.py
scales/sink.py
scales/timer_queue.py
scales/varz.py
scales/http/__init__.py
scales/http/builder.py
scales/http/sink.py
scales/kafka/__init__.py
scales/kafka/builder.py
scales/kafka/protocol.py
scales/kafka/sink.py
scales/loadbalancer/__init__.py
scales/loadbalancer/aperture.py
scales/loadbalancer/base.py
scales/loadbalancer/heap.py
scales/loadbalancer/serverset.py
scales/loadbalancer/zookeeper.py
scales/mux/__init__.py
scales/mux/sink.py
scales/pool/__init__.py
scales/pool/base.py
scales/pool/singleton.py
scales/pool/watermark.py
scales/redis/__init__.py
scales/redis/builder.py
scales/redis/sink.py
scales/thrift/__init__.py
scales/thrift/builder.py
scales/thrift/protocol.py
scales/thrift/serializer.py
scales/thrift/sink.py
scales/thrifthttp/__init__.py
scales/thrifthttp/builder.py
scales/thrifthttp/sink.py
scales/thriftmux/__init__.py
scales/thriftmux/builder.py
scales/thriftmux/protocol.py
scales/thriftmux/serializer.py
scales/thriftmux/sink.py
scales_rpc-2.0.1.dist-info/LICENSE.txt
scales_rpc-2.0.1.dist-info/METADATA
scales_rpc-2.0.1.dist-info/WHEEL
scales_rpc-2.0.1.dist-info/top_level.txt
scales_rpc-2.0.1.dist-info/RECORD
